dupont_contraction-2.1.0-py3.8-nspkg.pth
dupontcontraction/examples_cubical.py
dupontcontraction/examples_simplicial.py
dupontcontraction/cubical/__init__.py
dupontcontraction/cubical/signed_ordered_set.py
dupontcontraction/cubical/dupontforms/__init__.py
dupontcontraction/cubical/dupontforms/binary_tree_generator.py
dupontcontraction/cubical/dupontforms/cubical_dupontforms.py
dupontcontraction/cubical/sullivanforms/__init__.py
dupontcontraction/cubical/sullivanforms/cubical_auxiliary_functions.py
dupontcontraction/cubical/sullivanforms/cubical_sullivanforms.py
dupontcontraction/simplicial/__init__.py
dupontcontraction/simplicial/dupontforms/__init__.py
dupontcontraction/simplicial/dupontforms/binary_tree_generator.py
dupontcontraction/simplicial/dupontforms/dupontforms.py
dupontcontraction/simplicial/sullivanforms/__init__.py
dupontcontraction/simplicial/sullivanforms/auxiliary_functions.py
dupontcontraction/simplicial/sullivanforms/sullivanforms.py
dupont_contraction-2.1.0.dist-info/LICENSE
dupont_contraction-2.1.0.dist-info/METADATA
dupont_contraction-2.1.0.dist-info/WHEEL
dupont_contraction-2.1.0.dist-info/namespace_packages.txt
dupont_contraction-2.1.0.dist-info/top_level.txt
dupont_contraction-2.1.0.dist-info/RECORD
