Metadata-Version: 2.1
Name: dupont-contraction
Version: 2.1.0
Summary: A package for computations using Sullivan and Dupont forms, and the Dupont contraction.
Home-page: https://github.com/DanielRobertNicoud/dupont-contraction
Author: Daniel Robert-Nicoud
Author-email: daniel.robertnicoud@gmail.com
License: UNKNOWN
Platform: UNKNOWN
